PyAudit/__init__.py
PyAudit/basics.py
PyAudit-1.0.3.dist-info/METADATA
PyAudit-1.0.3.dist-info/WHEEL
PyAudit-1.0.3.dist-info/top_level.txt
PyAudit-1.0.3.dist-info/RECORD
